[
  {
    "tonnazh": "1",
    "type": "Тент",
    "hour": "8:00",
    "podacha": 1,
    "expeditor": 1,
    "tarifStavka": 4900,
    "pererabotkaHour": 490,
    "hydrobort": 490,
    "point": 560,
    "border": 0,
    "cost": 16,
    "loader": 1400
  },
  {
    "tonnazh": "1,5",
    "type": "Тент",
    "hour": "8:00",
    "podacha": 1,
    "expeditor": 1,
    "tarifStavka": 5500,
    "pererabotkaHour": 550,
    "hydrobort": 550,
    "point": 600,
    "border": 0,
    "cost": 18,
    "loader": 1600
  },
  {
    "tonnazh": "3",
    "type": "Тент",
    "hour": "8:00",
    "podacha": 1,
    "expeditor": 1,
    "tarifStavka": 7800,
    "pererabotkaHour": 780,
    "hydrobort": 780,
    "point": 830,
    "border": 0,
    "cost": 20,
    "loader": 1800
  },
  {
    "tonnazh": "5",
    "type": "Тент",
    "hour": "8:00",
    "podacha": 1,
    "expeditor": 1,
    "tarifStavka": 9500,
    "pererabotkaHour": 950,
    "hydrobort": 950,
    "point": 1000,
    "border": 0,
    "cost": 22,
    "loader": 2000
  },
  {
    "tonnazh": "7",
    "type": "Тент",
    "hour": "8:00",
    "podacha": 1,
    "expeditor": 1,
    "tarifStavka": 10000,
    "pererabotkaHour": 1000,
    "hydrobort": 1000,
    "point": 1050,
    "border": 0,
    "cost": 24,
    "loader": 2200
  },
  {
    "tonnazh": "10",
    "type": "Тент",
    "hour": "8:00",
    "podacha": 1,
    "expeditor": 1,
    "tarifStavka": 12000,
    "pererabotkaHour": 1200,
    "hydrobort": 1200,
    "point": 1250,
    "border": 0,
    "cost": 26,
    "loader": 2400
  },
  {
    "tonnazh": "20",
    "type": "Тент",
    "hour": "8:00",
    "podacha": 1,
    "expeditor": 1,
    "tarifStavka": 14000,
    "pererabotkaHour": 1400,
    "hydrobort": 1400,
    "point": 1450,
    "border": 0,
    "cost": 28,
    "loader": 2600
  }
]